README.md
setup.py
proxy6/__init__.py
proxy6/commander.py
proxy6/errors.py
proxy6.egg-info/PKG-INFO
proxy6.egg-info/SOURCES.txt
proxy6.egg-info/dependency_links.txt
proxy6.egg-info/entry_points.txt
proxy6.egg-info/top_level.txt
proxy6/client/__init__.py
proxy6/crawlers/__init__.py
proxy6/models/__init__.py
proxy6/server/__init__.py
proxy6/utils/__init__.py
proxy6/utils/object_dict.py
proxy6/utils/path.py
tests/__init__.py
tests/test.py