Metadata-Version: 1.1
Name: proxy6
Version: 0.0.3
Summary: A 2/3 compatible crawler http proxy pool.
Home-page: https://github.com/xlzd/proxy6
Author: xlzd
Author-email: i@xlzd.me
License: MIT
Platform: UNKNOWN
Classifier: License :: OSI Approved :: MIT License
Classifier: Environment :: Console
Classifier: Topic :: Internet
Classifier: Programming Language :: Python
Classifier: Programming Language :: Python :: 2
Classifier: Programming Language :: Python :: 2.7
Classifier: Programming Language :: Python :: 3
Classifier: Programming Language :: Python :: 3.4
Classifier: Programming Language :: Python :: 3.5
Classifier: Programming Language :: Python :: 3.6
